protobin/__init__.py
protobin/errors.py
protobin/fields.py
protobin/interfaces.py
protobin/protocol.py
protobin/singleton.py
protobin-0.1.0.dist-info/METADATA
protobin-0.1.0.dist-info/WHEEL
protobin-0.1.0.dist-info/licenses/LICENSE.txt
protobin-0.1.0.dist-info/RECORD
