Metadata-Version: 2.4
Name: protobin
Version: 0.1.0
Summary: Python library for encode and decode data in protobin format
Project-URL: Homepage, https://github.com/drmelectronic/protobin-python
Project-URL: Bug Tracker, https://github.com/drmelectronic/protobin-python/issues
Author-email: Daniel Robles <drm.electronic@gmail.com>
License: MIT License
License-File: LICENSE.txt
Classifier: License :: OSI Approved :: MIT License
Classifier: Operating System :: OS Independent
Classifier: Programming Language :: Python :: 3
Requires-Python: >=3.8
Requires-Dist: crcmod==1.7
Requires-Dist: pyyaml~=6.0
